[
  {
    "BrandName": "vw",
    "Model": "golf",
    "BodyType": "Sedan",
    "NDoors": 4,
    "EngineCap": 1900,
    "HorsePower": 110,
    "ProductionDate": "2005-12-10T00:00:00",
    "Price": 2200.00,
    "Color": "red",
    "ColorType": "Acrylic",
    "Fuel": "Diesel",
    "Gearbox": "Automatic",
    "NumberOfGears": 5,
    "Extras": ["abs", "esp"]
  },
  {
    "BrandName": "vw",
    "Model": "passat",
    "BodyType": "Sedan",
    "NDoors": 4,
    "EngineCap": 1800,
    "HorsePower": 150,
    "ProductionDate": "2008-05-07T00:00:00",
    "Price": 4800.00,
    "Color": "blue",
    "ColorType": "Acrylic",
    "Fuel": "LPG",
    "Gearbox": "Manual",
    "NumberOfGears": 6,
    "Extras": []
  }
]